<?xml version="1.0" encoding="UTF-8"?>
<drumkit_info>
 <name>change this name</name>
 <author></author>
 <info>&lt;!DOCTYPE HTML PUBLIC "-//W3C//DTD HTML 4.0//EN" "http://www.w3.org/TR/REC-html40/strict.dtd">
&lt;html>&lt;head>&lt;meta name="qrichtext" content="1" />&lt;style type="text/css">
p, li { white-space: pre-wrap; }
&lt;/style>&lt;/head>&lt;body style=" font-family:'Lucida Grande'; font-size:10pt; font-weight:400; font-style:normal;">
&lt;p style=" margin-top:0px; margin-bottom:0px; margin-left:0px; margin-right:0px; -qt-block-indent:0; text-indent:0px;">Drum kit.&lt;/p>&lt;/body>&lt;/html></info>
 <license>undefined license</license>
 
 <instrumentList> 
 </instrumentList>


</drumkit_info>
